nni
nni\algorithms
nni\algorithms\feature_engineering
nni\algorithms\feature_engineering\gbdt_selector
nni\algorithms\feature_engineering\gradient_selector
nni\algorithms\hpo
nni\algorithms\hpo\bohb_advisor
nni\algorithms\hpo\curvefitting_assessor
nni\algorithms\hpo\gp_tuner
nni\algorithms\hpo\metis_tuner
nni\algorithms\hpo\metis_tuner\Regression_GMM
nni\algorithms\hpo\metis_tuner\Regression_GP
nni\algorithms\hpo\networkmorphism_tuner
nni\algorithms\hpo\ppo_tuner
nni\algorithms\hpo\smac_tuner
nni\common
nni\common\concrete_trace_utils
nni\common\hpo_utils
nni\compression
nni\compression\base
nni\compression\distillation
nni\compression\pruning
nni\compression\pruning\tools
nni\compression\quantization
nni\compression\quantization_speedup
nni\compression\speedup
nni\compression\utils
nni\compression\utils\external
nni\compression\utils\quantization
nni\contrib
nni\contrib\distillation
nni\contrib\training_service
nni\experiment
nni\experiment\config
nni\experiment\config\training_services
nni\experiment\config\utils
nni\feature_engineering
nni\mutable
nni\nas
nni\nas\benchmark
nni\nas\benchmark\nasbench101
nni\nas\benchmark\nasbench201
nni\nas\benchmark\nds
nni\nas\benchmark\nlp
nni\nas\evaluator
nni\nas\evaluator\pytorch
nni\nas\evaluator\pytorch\cgo
nni\nas\execution
nni\nas\execution\cgo
nni\nas\execution\cgo\logical_optimizer
nni\nas\experiment
nni\nas\experiment\config
nni\nas\hub
nni\nas\hub\pytorch
nni\nas\hub\pytorch\modules
nni\nas\hub\pytorch\utils
nni\nas\nn
nni\nas\nn\pytorch
nni\nas\nn\tensorflow
nni\nas\oneshot
nni\nas\oneshot\pytorch
nni\nas\oneshot\pytorch\supermodule
nni\nas\profiler
nni\nas\profiler\pytorch
nni\nas\profiler\pytorch\utils
nni\nas\space
nni\nas\space\pytorch
nni\nas\space\pytorch\converter
nni\nas\space\tensorflow
nni\nas\strategy
nni\nas\utils
nni\runtime
nni\runtime\command_channel
nni\runtime\command_channel\websocket
nni\runtime\default_config
nni\runtime\trial_command_channel
nni\runtime\tuner_command_channel
nni\tools
