Metadata-Version: 2.1
Name: nni
Version: 3.0
Summary: Neural Network Intelligence project
Home-page: https://github.com/Microsoft/nni
Author: Microsoft NNI Team
Author-email: nni@microsoft.com
License: MIT
Classifier: License :: OSI Approved :: MIT License
Classifier: Operating System :: MacOS :: MacOS X
Classifier: Operating System :: Microsoft :: Windows :: Windows 10
Classifier: Operating System :: POSIX :: Linux
Classifier: Programming Language :: Python :: 3 :: Only
Classifier: Topic :: Scientific/Engineering :: Artificial Intelligence
Requires-Python: >=3.7
License-File: LICENSE
Requires-Dist: astor
Requires-Dist: cloudpickle
Requires-Dist: colorama
Requires-Dist: filelock <3.12
Requires-Dist: json-tricks >=3.15.5
Requires-Dist: nvidia-ml-py
Requires-Dist: packaging
Requires-Dist: pandas
Requires-Dist: prettytable
Requires-Dist: psutil
Requires-Dist: PythonWebHDFS
Requires-Dist: pyyaml >=5.4
Requires-Dist: requests
Requires-Dist: responses
Requires-Dist: schema
Requires-Dist: scikit-learn >=0.24.1
Requires-Dist: tqdm
Requires-Dist: typeguard <4.1.3,>=3.0.0
Requires-Dist: typing-extensions >=4.7.0
Requires-Dist: websockets >=10.1
Requires-Dist: numpy <1.22 ; python_version < "3.8"
Requires-Dist: scipy <1.8 ; python_version < "3.8"
Requires-Dist: numpy ; python_version >= "3.8"
Requires-Dist: scipy ; python_version >= "3.8"
Provides-Extra: anneal
Requires-Dist: hyperopt ==0.1.2 ; extra == 'anneal'
Provides-Extra: bohb
Requires-Dist: ConfigSpace >=0.4.17 ; extra == 'bohb'
Requires-Dist: statsmodels >=0.12.0 ; extra == 'bohb'
Provides-Extra: dngo
Requires-Dist: pybnn ; extra == 'dngo'
Provides-Extra: ppotuner
Requires-Dist: gym ; extra == 'ppotuner'
Provides-Extra: smac
Requires-Dist: ConfigSpaceNNI >=0.4.7.3 ; extra == 'smac'
Requires-Dist: smac4nni ; extra == 'smac'
Provides-Extra: all
Requires-Dist: hyperopt ==0.1.2 ; extra == 'all'
Requires-Dist: ConfigSpaceNNI >=0.4.7.3 ; extra == 'all'
Requires-Dist: smac4nni ; extra == 'all'
Requires-Dist: ConfigSpace >=0.4.17 ; extra == 'all'
Requires-Dist: statsmodels >=0.12.0 ; extra == 'all'
Requires-Dist: gym ; extra == 'all'
Requires-Dist: pybnn ; extra == 'all'
